{
	"textures": [
		{
			"image": "zangiefFrontBack.png",
			"format": "RGBA8888",
			"size": {
				"w": 1024,
				"h": 512
			},
			"scale": 1,
			"frames": [
				{
					"filename": "zangiefBack.png",
					"rotated": false,
					"trimmed": false,
					"sourceSize": {
						"w": 512,
						"h": 512
					},
					"spriteSourceSize": {
						"x": 0,
						"y": 0,
						"w": 512,
						"h": 512
					},
					"frame": {
						"x": 0,
						"y": 0,
						"w": 512,
						"h": 512
					}
				},
				{
					"filename": "zangiefFront.png",
					"rotated": false,
					"trimmed": false,
					"sourceSize": {
						"w": 512,
						"h": 512
					},
					"spriteSourceSize": {
						"x": 0,
						"y": 0,
						"w": 512,
						"h": 512
					},
					"frame": {
						"x": 512,
						"y": 0,
						"w": 512,
						"h": 512
					}
				}
			]
		}
	],
	"meta": {
		"app": "https://www.codeandweb.com/texturepacker",
		"version": "3.0",
		"smartupdate": "$TexturePacker:SmartUpdate:d2ef05639a17374e693d2f4647d8f80d:2a0bf1a8b286c40486802d2f948594a2:d3c7d58a093227dfa02cf6e24055c0c7$"
	}
}
